augint_cosmic/__init__.py
augint_cosmic/cosmic_connect.py
augint_cosmic/util.py
augint_cosmic-2.0.1.dist-info/LICENSE
augint_cosmic-2.0.1.dist-info/METADATA
augint_cosmic-2.0.1.dist-info/WHEEL
augint_cosmic-2.0.1.dist-info/entry_points.txt
augint_cosmic-2.0.1.dist-info/RECORD
