Metadata-Version: 2.3
Name: augint-cosmic
Version: 2.0.1
Summary: A template library for Python library projects using Poetry and Semantic Release.
License: Copyright (c) Augmenting Integrations LLC
Author: Samuel Vange
Author-email: 7166607+svange@users.noreply.github.com
Requires-Python: >=3.10,<4.0
Classifier: License :: Other/Proprietary License
Classifier: Programming Language :: Python :: 3
Classifier: Programming Language :: Python :: 3.10
Classifier: Programming Language :: Python :: 3.11
Classifier: Programming Language :: Python :: 3.12
Classifier: Programming Language :: Python :: 3.13
Requires-Dist: boto3 (>=1.39.3,<2.0.0)
Requires-Dist: click (>=8.1.0,<8.2.0)
Requires-Dist: cryptography (>=45.0.5,<46.0.0)
Requires-Dist: python-dotenv (>=1.1.1,<2.0.0)
